ape_dasy/__init__.py
ape_dasy/compiler.py
ape_dasy-0.1.2.dist-info/METADATA
ape_dasy-0.1.2.dist-info/WHEEL
ape_dasy-0.1.2.dist-info/RECORD
